Workbook

Sheet Dashboard
A1: FINANCIAL HEALTH DASHBOARD
A2: SME Financial Overview | FY 2024 | All figures in $000s
A4: Total Revenue | B4: Total Expenses | C4: Net Profit | D4: Gross Margin | E4: EBITDA Margin | F4: Net Margin | G4: Current Ratio | H4: Debt/Equity
A5: =Income!G5 -> -2177.444 | B5: =Income!G8 -> 1108.5169 | C5: =Income!G14 -> 781.13769 | D5: =Income!G17 -> 0.28 | E5: =Income!G20 -> 0 | F5: =Income!G22 -> 0 | G5: =Ratios!C5 -> >2.0 | H5: =Ratios!C8 -> 0
A6: FY 2024 | B6: FY 2024 | C6: FY 2024 | D6: FY 2024 | E6: FY 2024 | F6: FY 2024 | G6: FY 2024 | H6: FY 2024
A8: NAVIGATE → Income Statement | Balance Sheet | Cash Flow | Ratios | Forecast | Assumptions

Sheet Assumptions
A1: ASSUMPTIONS & INPUTS
A2: Blue = Input cells (change to model scenarios)
A3: Assumption | B3: Value | C3: Unit | D3: Note | E3: Source
A4: ── REVENUE ──
A5: Base Revenue (Q1 2024) | B5: 820 | C5: $000 | D5: Starting quarterly revenue | E5: Management estimate
A6: Revenue Growth Q2 | B6: 0.146 | C6: % | D6: Q-o-Q growth rate | E6: Historical avg
A7: Revenue Growth Q3 | B7: 0.085 | C7: % | D7: Q-o-Q growth rate | E7: Historical avg
A8: Revenue Growth Q4 | B8: 0.157 | C8: % | D8: Q-o-Q growth rate | E8: Historical avg
A9: ── MARGINS ──
A10: COGS % of Revenue | B10: 0.55 | C10: % | D10: Cost of goods sold ratio | E10: Industry benchmark
A11: Operating Expense % | B11: 0.17 | C11: % | D11: SG&A + other opex | E11: Budget FY2024
A12: Depreciation ($000) | B12: 45 | C12: $000 | D12: Annual depreciation | E12: Fixed asset schedule
A13: Interest Expense ($000) | B13: 22 | C13: $000 | D13: Annual interest cost | E13: Loan agreement
A14: Tax Rate | B14: 0.25 | C14: % | D14: Effective corporate tax | E14: Tax advisory
A15: ── BALANCE SHEET ──
A16: Starting Total Assets | B16: 2100 | C16: $000 | D16: Q1 2024 assets | E16: Prior period BS
A17: Starting Total Liabilities | B17: 900 | C17: $000 | D17: Q1 2024 liabilities | E17: Prior period BS
A18: ── FORECAST ──
A19: Forecast Growth Rate Q1 2025 | B19: 0.11 | C19: % | D19: Conservative estimate | E19: Analyst consensus
A20: Forecast Growth Rate Q2 2025 | B20: 0.092 | C20: % | D20: Conservative estimate | E20: Analyst consensus
A21: Forecast Growth Rate Q3 2025 | B21: 0.091 | C21: % | D21: Conservative estimate | E21: Analyst consensus
A22: Forecast Growth Rate Q4 2025 | B22: 0.09 | C22: % | D22: Conservative estimate | E22: Analyst consensus
A23: Confidence Interval | B23: 0.15 | C23: % | D23: ± band around forecast | E23: Statistical model

Sheet Income
A1: INCOME STATEMENT
A2: All figures in $000s | Black = formula | Blue = input
B3: Q1 2024 | C3: Q2 2024 | D3: Q3 2024 | E3: Q4 2024 | G3: FY 2024
A4: Revenue | B4: =Assumptions!B5 -> 820 | C4: =B4*(1+Assumptions!B6) -> 939.72 | D4: =C4*(1+Assumptions!B7) -> 1019.5962 | E4: =D4*(1+Assumptions!B8) -> 1179.6728 | G4: =SUM(B4:E4) -> 3958.989
A5: Cost of Goods Sold (COGS) | B5: =-B4*Assumptions!$B$10 -> -451 | C5: =-C4*Assumptions!$B$10 -> -516.846 | D5: =-D4*Assumptions!$B$10 -> -560.77791 | E5: =-E4*Assumptions!$B$10 -> -648.82004 | G5: =SUM(B5:E5) -> -2177.444
A6: Gross Profit | B6: =B4+B5 -> 369 | C6: =C4+C5 -> 422.874 | D6: =D4+D5 -> 458.81829 | E6: =E4+E5 -> 530.85276 | G6: =SUM(B6:E6) -> 1781.5451
A7: Operating Expenses (SG&A) | B7: =-B4*Assumptions!$B$11 -> -139.4 | C7: =-C4*Assumptions!$B$11 -> -159.7524 | D7: =-D4*Assumptions!$B$11 -> -173.33135 | E7: =-E4*Assumptions!$B$11 -> -200.54438 | G7: =SUM(B7:E7) -> -673.02813
A8: EBITDA | B8: =B6+B7 -> 229.6 | C8: =C6+C7 -> 263.1216 | D8: =D6+D7 -> 285.48694 | E8: =E6+E7 -> 330.30838 | G8: =SUM(B8:E8) -> 1108.5169
A9: Depreciation & Amortization | B9: =-Assumptions!$B$12/4 -> -11.25 | C9: =-Assumptions!$B$12/4 -> -11.25 | D9: =-Assumptions!$B$12/4 -> -11.25 | E9: =-Assumptions!$B$12/4 -> -11.25 | G9: =SUM(B9:E9) -> -45
A10: EBIT (Operating Profit) | B10: =B8+B9 -> 218.35 | C10: =C8+C9 -> 251.8716 | D10: =D8+D9 -> 274.23694 | E10: =E8+E9 -> 319.05838 | G10: =SUM(B10:E10) -> 1063.5169
A11: Interest Expense | B11: =-Assumptions!$B$13/4 -> -5.5 | C11: =-Assumptions!$B$13/4 -> -5.5 | D11: =-Assumptions!$B$13/4 -> -5.5 | E11: =-Assumptions!$B$13/4 -> -5.5 | G11: =SUM(B11:E11) -> -22
A12: EBT (Earnings Before Tax) | B12: =B10+B11 -> 212.85 | C12: =C10+C11 -> 246.3716 | D12: =D10+D11 -> 268.73694 | E12: =E10+E11 -> 313.55838 | G12: =SUM(B12:E12) -> 1041.5169
A13: Income Tax | B13: =-B12*Assumptions!$B$14 -> -53.2125 | C13: =-C12*Assumptions!$B$14 -> -61.5929 | D13: =-D12*Assumptions!$B$14 -> -67.184234 | E13: =-E12*Assumptions!$B$14 -> -78.389596 | G13: =SUM(B13:E13) -> -260.37923
A14: NET PROFIT | B14: =B12+B13 -> 159.6375 | C14: =C12+C13 -> 184.7787 | D14: =D12+D13 -> 201.5527 | E14: =E12+E13 -> 235.16879 | G14: =SUM(B14:E14) -> 781.13769
A15: PROFITABILITY MARGINS
A16: Gross Margin % | B16: =IF(B4<>0,B6/B4,0) -> 0.45 | C16: =IF(C4<>0,C6/C4,0) -> 0.45 | D16: =IF(D4<>0,D6/D4,0) -> 0.45 | E16: =IF(E4<>0,E6/E4,0) -> 0.45 | G16: =IF(G4<>0,G6/G4,0) -> 0.45
A17: EBITDA Margin % | B17: =IF(B4<>0,B8/B4,0) -> 0.28 | C17: =IF(C4<>0,C8/C4,0) -> 0.28 | D17: =IF(D4<>0,D8/D4,0) -> 0.28 | E17: =IF(E4<>0,E8/E4,0) -> 0.28 | G17: =IF(G4<>0,G8/G4,0) -> 0.28
A18: EBIT Margin % | B18: =IF(B4<>0,B10/B4,0) -> 0.26628049 | C18: =IF(C4<>0,C10/C4,0) -> 0.26802835 | D18: =IF(D4<>0,D10/D4,0) -> 0.26896622 | E18: =IF(E4<>0,E10/E4,0) -> 0.27046346 | G18: =IF(G4<>0,G10/G4,0) -> 0.26863346
A19: Net Margin % | B19: =IF(B4<>0,B14/B4,0) -> 0.19467988 | C19: =IF(C4<>0,C14/C4,0) -> 0.19663166 | D19: =IF(D4<>0,D14/D4,0) -> 0.19767895 | E19: =IF(E4<>0,E14/E4,0) -> 0.19935086 | G19: =IF(G4<>0,G14/G4,0) -> 0.19730737

Sheet BalanceSheet
A1: BALANCE SHEET
A2: All figures in $000s
B3: Q1 2024 | C3: Q2 2024 | D3: Q3 2024 | E3: Q4 2024 | G3: FY 2024
A4: ASSETS
A5: Cash & Cash Equivalents | B5: 680 | C5: 750 | D5: 820 | E5: 920 | G5: =E5 -> 920
A6: Accounts Receivable | B6: 320 | C6: 350 | D6: 380 | E6: 410 | G6: =E6 -> 410
A7: Inventory | B7: 240 | C7: 260 | D7: 270 | E7: 300 | G7: =E7 -> 300
A8: Other Current Assets | B8: 60 | C8: 65 | D8: 70 | E8: 75 | G8: =E8 -> 75
A9: Total Current Assets | B9: =SUM(B5:B8) -> 1300 | C9: =SUM(C5:C8) -> 1425 | D9: =SUM(D5:D8) -> 1540 | E9: =SUM(E5:E8) -> 1705 | G9: =E9 -> 1705
A10: Property, Plant & Equipment | B10: 900 | C10: 920 | D10: 940 | E10: 960 | G10: =E10 -> 960
A11: Less: Accumulated Depreciation | B11: -180 | C11: -191 | D11: -202 | E11: -213 | G11: =E11 -> -213
A12: Intangible Assets | B12: 150 | C12: 160 | D12: 165 | E12: 170 | G12: =E12 -> 170
A13: Long-term Investments | B13: 170 | C13: 178 | D13: 185 | E13: 195 | G13: =E13 -> 195
A14: Total Assets | B14: =B9+SUM(B10:B13) -> 2340 | C14: =C9+SUM(C10:C13) -> 2492 | D14: =D9+SUM(D10:D13) -> 2628 | E14: =E9+SUM(E10:E13) -> 2817 | G14: =E14 -> 2817
A15: LIABILITIES & EQUITY
A16: Accounts Payable | B16: 180 | C16: 190 | D16: 200 | E16: 215 | G16: =E16 -> 215
A17: Short-term Debt | B17: 120 | C17: 110 | D17: 105 | E17: 100 | G17: =E17 -> 100
A18: Accrued Liabilities | B18: 80 | C18: 85 | D18: 90 | E18: 95 | G18: =E18 -> 95
A19: Other Current Liabilities | B19: 40 | C19: 42 | D19: 45 | E19: 48 | G19: =E19 -> 48
A20: Total Current Liabilities | B20: =SUM(B16:B19) -> 420 | C20: =SUM(C16:C19) -> 427 | D20: =SUM(D16:D19) -> 440 | E20: =SUM(E16:E19) -> 458 | G20: =E20 -> 458
A21: Long-term Debt | B21: 380 | C21: 370 | D21: 360 | E21: 345 | G21: =E21 -> 345
A22: Deferred Tax Liability | B22: 100 | C22: 103 | D22: 106 | E22: 110 | G22: =E22 -> 110
A23: Total Liabilities | B23: =B20+SUM(B21:B22) -> 900 | C23: =C20+SUM(C21:C22) -> 900 | D23: =D20+SUM(D21:D22) -> 906 | E23: =E20+SUM(E21:E22) -> 913 | G23: =E23 -> 913
A24: Share Capital | B24: 500 | C24: 500 | D24: 500 | E24: 500 | G24: =E24 -> 500
A25: Retained Earnings | B25: 600 | C25: 757 | D25: 927 | E25: 1097 | G25: =E25 -> 1097
A26: Other Reserves | B26: 200 | C26: 205 | D26: 210 | E26: 215 | G26: =E26 -> 215
A27: Total Equity | B27: =SUM(B24:B26) -> 1300 | C27: =SUM(C24:C26) -> 1462 | D27: =SUM(D24:D26) -> 1637 | E27: =SUM(E24:E26) -> 1812 | G27: =E27 -> 1812
A28: Total Liabilities + Equity | B28: =B23+B27 -> 2200 | C28: =C23+C27 -> 2362 | D28: =D23+D27 -> 2543 | E28: =E23+E27 -> 2725 | G28: =E28 -> 2725
A29: Balance Check (Assets - L&E) | B29: =B14-B28 -> 140 | C29: =C14-C28 -> 130 | D29: =D14-D28 -> 85 | E29: =E14-E28 -> 92 | G29: =E29 -> 92

Sheet CashFlow
A1: CASH FLOW STATEMENT
A2: All figures in $000s
B3: Q1 2024 | C3: Q2 2024 | D3: Q3 2024 | E3: Q4 2024 | G3: FY 2024
A4: OPERATING ACTIVITIES
A5: Net Profit | B5: =Income!B14 -> 159.6375 | C5: =Income!C14 -> 184.7787 | D5: =Income!D14 -> 201.5527 | E5: =Income!E14 -> 235.16879 | G5: =SUM(B5:E5) -> 781.13769
A6: Add: Depreciation | B6: 12 | C6: 12 | D6: 11 | E6: 10 | G6: =SUM(B6:E6) -> 45
A7: Change in Accounts Receivable | B7: -22 | C7: -30 | D7: -20 | E7: -30 | G7: =SUM(B7:E7) -> -102
A8: Change in Inventory | B8: -15 | C8: -20 | D8: -10 | E8: -30 | G8: =SUM(B8:E8) -> -75
A9: Change in Accounts Payable | B9: 10 | C9: 10 | D9: 10 | E9: 15 | G9: =SUM(B9:E9) -> 45
A10: Other Working Capital Changes | B10: 5 | C10: 8 | D10: 7 | E10: 6 | G10: =SUM(B10:E10) -> 26
A11: Net Cash from Operations | B11: =SUM(B5:B10) -> 149.6375 | C11: =SUM(C5:C10) -> 164.7787 | D11: =SUM(D5:D10) -> 199.5527 | E11: =SUM(E5:E10) -> 206.16879 | G11: =SUM(B11:E11) -> 720.13769
A12: INVESTING ACTIVITIES
A13: Capital Expenditures (CapEx) | B13: -80 | C13: -100 | D13: -90 | E13: -120 | G13: =SUM(B13:E13) -> -390
A14: Purchase of Investments | B14: -20 | C14: -15 | D14: -18 | E14: -22 | G14: =SUM(B14:E14) -> -75
A15: Proceeds from Asset Disposal | B15: 10 | C15: 5 | D15: 8 | E15: 12 | G15: =SUM(B15:E15) -> 35
A16: Net Cash from Investing | B16: =SUM(B13:B15) -> -90 | C16: =SUM(C13:C15) -> -110 | D16: =SUM(D13:D15) -> -100 | E16: =SUM(E13:E15) -> -130 | G16: =SUM(B16:E16) -> -430
A17: FINANCING ACTIVITIES
A18: Loan Repayments | B18: -30 | C18: -30 | D18: -30 | E18: -30 | G18: =SUM(B18:E18) -> -120
A19: Dividends Paid | B19: -20 | C19: -20 | D19: -20 | E19: -20 | G19: =SUM(B19:E19) -> -80
A20: New Equity Raised | B20: 0 | C20: 0 | D20: 0 | E20: 0 | G20: =SUM(B20:E20) -> 0
A21: Net Cash from Financing | B21: =SUM(B18:B20) -> -50 | C21: =SUM(C18:C20) -> -50 | D21: =SUM(D18:D20) -> -50 | E21: =SUM(E18:E20) -> -50 | G21: =SUM(B21:E21) -> -200
A22: NET CHANGE IN CASH | B22: =B11+B16+B21 -> 9.6375 | C22: =C11+C16+C21 -> 4.7787 | D22: =D11+D16+D21 -> 49.552702 | E22: =E11+E16+E21 -> 26.168789 | G22: =B22+C22+D22+E22 -> 90.137691

Sheet Ratios
A1: KEY FINANCIAL RATIOS
A2: Based on Q4 2024 / FY 2024 data
A3: Ratio | B3: Value | C3: Benchmark | D3: Interpretation | E3: Status
A4: ── LIQUIDITY ──
A5: Current Ratio | B5: =BalanceSheet!E9/BalanceSheet!E20 -> 3.7227074 | C5: >2.0 | D5: Ability to cover short-term obligations | E5: =IF(B5<>"","✓ On Track","–") -> ✓ On Track
A6: Quick Ratio | B6: =(BalanceSheet!E5+BalanceSheet!E6)/BalanceSheet!E20 -> 2.9039301 | C6: >1.0 | D6: Liquid assets vs current liabilities | E6: =IF(B6<>"","✓ On Track","–") -> ✓ On Track
A7: Cash Ratio | B7: =BalanceSheet!E5/BalanceSheet!E20 -> 2.0087336 | C7: >0.5 | D7: Cash coverage of current liabilities | E7: =IF(B7<>"","✓ On Track","–") -> ✓ On Track
A8: ── PROFITABILITY ──
A9: Return on Equity (ROE) | B9: =Income!G14/BalanceSheet!E27 -> 0.43109144 | C9: >15% | D9: Net profit as % of equity | E9: =IF(B9<>"","✓ On Track","–") -> ✓ On Track
A10: Return on Assets (ROA) | B10: =Income!G14/BalanceSheet!E14 -> 0.27729417 | C10: >8% | D10: Net profit as % of total assets | E10: =IF(B10<>"","✓ On Track","–") -> ✓ On Track
A11: Return on Investment | B11: =Income!G14/(BalanceSheet!E14-BalanceSheet!E23) -> 0.41026139 | C11: >12% | D11: Net profit as % of invested capital | E11: =IF(B11<>"","✓ On Track","–") -> ✓ On Track
A12: ── SOLVENCY ──
A13: Debt-to-Equity | B13: =BalanceSheet!E23/BalanceSheet!E27 -> 0.50386313 | C13: <0.8 | D13: Financial leverage ratio | E13: =IF(B13<>"","✓ On Track","–") -> ✓ On Track
A14: Debt-to-Assets | B14: =BalanceSheet!E23/BalanceSheet!E14 -> 0.32410366 | C14: <0.5 | D14: Proportion of assets financed by debt | E14: =IF(B14<>"","✓ On Track","–") -> ✓ On Track
A15: Interest Coverage | B15: =Income!G10/(-Income!G11) -> 48.341678 | C15: >3.0x | D15: EBIT / Interest expense | E15: =IF(B15<>"","✓ On Track","–") -> ✓ On Track
A16: ── EFFICIENCY ──
A17: Asset Turnover | B17: =Income!G4/BalanceSheet!E14 -> 1.4053919 | C17: >0.4x | D17: Revenue generated per $ of assets | E17: =IF(B17<>"","✓ On Track","–") -> ✓ On Track
A18: Inventory Days | B18: =(BalanceSheet!E7/(-Income!G5))*365 -> 50.288321 | C18: <45 days | D18: Days to turn inventory into sales | E18: =IF(B18<>"","✓ On Track","–") -> ✓ On Track
A19: Receivables Days | B19: =(BalanceSheet!E6/Income!G4)*365 -> 37.800054 | C19: <45 days | D19: Average collection period | E19: =IF(B19<>"","✓ On Track","–") -> ✓ On Track

Sheet Forecast
A1: REVENUE FORECAST & FINANCIAL PLANNING
A2: Forecast based on Assumptions sheet | Adjust growth rates in Assumptions!B16:B19
B3: Q1 2024 | C3: Q2 2024 | D3: Q3 2024 | E3: Q4 2024 | F3: Q1 2025F | G3: Q2 2025F | H3: Q3 2025F
A4: ACTUALS (FY 2024)
A5: Revenue ($000) | B5: =Income!B4 -> 820 | C5: =Income!C4 -> 939.72 | D5: =Income!D4 -> 1019.5962 | E5: =Income!E4 -> 1179.6728
A6: Gross Profit ($000) | B6: =Income!B6 -> 369 | C6: =Income!C6 -> 422.874 | D6: =Income!D6 -> 458.81829 | E6: =Income!E6 -> 530.85276
A7: EBITDA ($000) | B7: =Income!B8 -> 229.6 | C7: =Income!C8 -> 263.1216 | D7: =Income!D8 -> 285.48694 | E7: =Income!E8 -> 330.30838
A8: Net Profit ($000) | B8: =Income!B14 -> 159.6375 | C8: =Income!C14 -> 184.7787 | D8: =Income!D14 -> 201.5527 | E8: =Income!E14 -> 235.16879
A9: Gross Margin % | B9: =Income!B16 -> 0.45 | C9: =Income!C16 -> 0.45 | D9: =Income!D16 -> 0.45 | E9: =Income!E16 -> 0.45
A10: Net Margin % | B10: =Income!B19 -> 0.19467988 | C10: =Income!C19 -> 0.19663166 | D10: =Income!D19 -> 0.19767895 | E10: =Income!E19 -> 0.19935086
A11: FORECAST (2025)
A12: Revenue Forecast ($000) | B12: =Income!E4 -> 1179.6728 | F12: =Income!E4*(1+Assumptions!B16) -> 2478492.6 | G12: =F12*(1+Assumptions!B17) -> 2.2331218e+09 | H12: =G12*(1+Assumptions!B18) -> 2.2331218e+09
A13: Forecast High (+CI) | F13: =F12*(1+Assumptions!$B$19) -> 2751126.7 | G13: =G12*(1+Assumptions!$B$19) -> 2.4787652e+09 | H13: =H12*(1+Assumptions!$B$19) -> 2.4787652e+09
A14: Forecast Low (-CI) | F14: =F12*(1-Assumptions!$B$19) -> 2205858.4 | G14: =G12*(1-Assumptions!$B$19) -> 1.9874784e+09 | H14: =H12*(1-Assumptions!$B$19) -> 1.9874784e+09
A15: PROJECTED P&L (based on FY2024 margins)
A16: Projected Gross Profit | F16: =F12*Assumptions!$B$10 -> 1363170.9 | G16: =G12*Assumptions!$B$10 -> 1.228217e+09 | H16: =H12*Assumptions!$B$10 -> 1.228217e+09
A17: Projected EBITDA | F17: =F16-F12*Assumptions!$B$11 -> 941827.17 | G17: =G16-G12*Assumptions!$B$11 -> 8.4858628e+08 | H17: =H16-H12*Assumptions!$B$11 -> 8.4858628e+08
A18: Projected Net Profit | F18: =F17*(1-Assumptions!$B$14) -> 706370.38 | G18: =G17*(1-Assumptions!$B$14) -> 6.3643971e+08 | H18: =H17*(1-Assumptions!$B$14) -> 6.3643971e+08
A19: Projected Gross Margin | F19: =F16/F12 -> 0.55 | G19: =G16/G12 -> 0.55 | H19: =H16/H12 -> 0.55
A20: Projected Net Margin | F20: =F18/F12 -> 0.285 | G20: =G18/G12 -> 0.285 | H20: =H18/H12 -> 0.285
